{
  "description": "Experiment: Survival=Lowest Fitness, Mate=Max Movement",
  "database_file": "database.sqlite",
  "num_simulators": 8,
  "evaluate": true,
  "simulation_headless": true,
  "visualize_map": false,
  "incubator_training_budget": 200,
  "population_size": 35,
  "min_population_size": 25,
  "max_population_size": 45,
  "max_age": 50,
  "iterations": 400,
  "field_x_min": -7,
  "field_x_max": 7,
  "field_y_min": -7,
  "field_y_max": 7,
  "fitness_function_algorithm": "MAX_DISTANCE",
  "mate_selection_strategy": "MAX_FITNESS",
  "mate_selection_threshold": 0.125,
  "mating_threshold": 1,
  "mating_cooldown": 3,
  "death_mechanism": "LOWEST_FITNESS",
  "movement_weight": 0.75
}
